forgepy/__init__.py
forgepy/module1.py
forgepy/module2.py
my_project/__init__.py
my_project/module1.py
my_project/module2.py
nautilus-forgepy/__init__.py
nautilus-forgepy/module1.py
nautilus-forgepy/module2.py
nautilus_forgepy-0.1.0.dist-info/METADATA
nautilus_forgepy-0.1.0.dist-info/WHEEL
nautilus_forgepy-0.1.0.dist-info/top_level.txt
nautilus_forgepy-0.1.0.dist-info/RECORD
