Metadata-Version: 2.1
Name: nautilus-forgepy
Version: 0.1.0
Summary: Algorand Python Smart Contract Library
Home-page: https://github.com/NautilusOSS/forgepy
Author: Nicholas Shellabarger
Author-email: enshellapypi@gmail.com
Classifier: Programming Language :: Python :: 3
Classifier: License :: OSI Approved :: MIT License
Classifier: Operating System :: OS Independent
Requires-Python: >=3.6
Requires-Dist: algorand-python>=1.3.0
